CHANGELOG.md
cloudmage/__init__.py
cloudmage/main.py
cloudmage-0.0.1.dist-info/entry_points.txt
cloudmage-0.0.1.dist-info/WHEEL
cloudmage-0.0.1.dist-info/METADATA
cloudmage-0.0.1.dist-info/RECORD
