Metadata-Version: 2.1
Name: cloudmage
Version: 0.0.1
Summary: Cloud Simplifaction and Automation Magic.
Home-page: https://github.com/TheCloudMage/PyPkgs-JinjaUtils
License: GPL-3.0-or-later
Author: Rich Nason
Author-email: rnason@cloudmage.io
Requires-Python: >=3.6,<4.0
Classifier: License :: OSI Approved :: GNU General Public License v3 or later (GPLv3+)
Classifier: Programming Language :: Python :: 3
Classifier: Programming Language :: Python :: 3.6
Classifier: Programming Language :: Python :: 3.7
Classifier: Programming Language :: Python :: 3.8
Project-URL: Bug Tracking, https://github.com/TheCloudMage/Common-Images/issues
Project-URL: Releases, https://github.com/TheCloudMage/Common-Images/releases
